labtasker/__init__.py
labtasker/__main__.py
labtasker/api_models.py
labtasker/constants.py
labtasker/filtering.py
labtasker/security.py
labtasker/utils.py
labtasker/client/__init__.py
labtasker/client/client_api.py
labtasker/client/cli/__init__.py
labtasker/client/cli/cli.py
labtasker/client/cli/config.py
labtasker/client/cli/event.py
labtasker/client/cli/init.py
labtasker/client/cli/loop.py
labtasker/client/cli/queue.py
labtasker/client/cli/task.py
labtasker/client/cli/worker.py
labtasker/client/core/__init__.py
labtasker/client/core/api.py
labtasker/client/core/cli_utils.py
labtasker/client/core/config.py
labtasker/client/core/context.py
labtasker/client/core/events.py
labtasker/client/core/exceptions.py
labtasker/client/core/heartbeat.py
labtasker/client/core/job_runner.py
labtasker/client/core/logging.py
labtasker/client/core/pager.py
labtasker/client/core/paths.py
labtasker/client/core/plugin_utils.py
labtasker/client/core/query_transpiler.py
labtasker/client/core/utils.py
labtasker/client/core/version_checker.py
labtasker/client/core/cmd_parser/LabCmd.g4
labtasker/client/core/cmd_parser/LabCmdLexer.g4
labtasker/client/core/cmd_parser/__init__.py
labtasker/client/core/cmd_parser/parser.py
labtasker/client/core/cmd_parser/generated/LabCmd.py
labtasker/client/core/cmd_parser/generated/LabCmdLexer.py
labtasker/client/core/cmd_parser/generated/LabCmdListener.py
labtasker/client/core/cmd_parser/generated/__init__.py
labtasker/client/core/resolver/__init__.py
labtasker/client/core/resolver/models.py
labtasker/client/core/resolver/utils.py
labtasker/client/templates/labtasker_root/.gitignore
labtasker/client/templates/labtasker_root/client.toml
labtasker/client/templates/labtasker_root/logs/.gitkeep
labtasker/server/__init__.py
labtasker/server/cli.py
labtasker/server/config.py
labtasker/server/database.py
labtasker/server/db_utils.py
labtasker/server/dependencies.py
labtasker/server/embedded_db.py
labtasker/server/endpoints.py
labtasker/server/event_manager.py
labtasker-0.2.12.dist-info/licenses/LICENSE
labtasker-0.2.12.dist-info/METADATA
labtasker-0.2.12.dist-info/WHEEL
labtasker-0.2.12.dist-info/entry_points.txt
labtasker-0.2.12.dist-info/top_level.txt
labtasker-0.2.12.dist-info/RECORD
