Metadata-Version: 2.4
Name: labtasker
Version: 0.2.12
Summary: A task queue system for lab experiments
Author-email: Your Name <your.email@example.com>
License: Apache License 2.0
Project-URL: Homepage, https://github.com/luocfprime/labtasker
Project-URL: Documentation, https://luocfprime.github.io/labtasker
Project-URL: Repository, https://github.com/luocfprime/labtasker.git
Classifier: Intended Audience :: Science/Research
Classifier: License :: OSI Approved :: Apache Software License
Classifier: Operating System :: OS Independent
Classifier: Programming Language :: Python :: 3
Classifier: Programming Language :: Python :: 3.10
Classifier: Programming Language :: Python :: 3.11
Classifier: Programming Language :: Python :: 3.12
Classifier: Programming Language :: Python :: 3.13
Requires-Python: <4.0,>=3.10
License-File: LICENSE
Requires-Dist: pymongo<5.0.0,>=4.0.0
Requires-Dist: fastapi<0.117.0,>=0.115.0
Requires-Dist: uvicorn[standard]<0.36.0,>=0.15.0
Requires-Dist: click<9.0.0,>=8.2.0
Requires-Dist: passlib<2.0.0,>=1.7.0
Requires-Dist: pydantic-settings<3.0.0,>=2.8.0
Requires-Dist: httpx[socks]<0.29.0,>=0.28.0
Requires-Dist: typer<0.17.0,>=0.16.0
Requires-Dist: loguru<0.8.0,>=0.7.0
Requires-Dist: ruamel-yaml<0.19.0,>=0.18.10
Requires-Dist: pyyaml<7.0.0,>=6.0.0
Requires-Dist: tomlkit<0.14.0,>=0.13.2
Requires-Dist: importlib-metadata<9.0.0,>=8.5.0
Requires-Dist: packaging<26.0,>=24.2
Requires-Dist: sse-starlette<4.0.0,>=2.1.3
Requires-Dist: httpx-sse<0.5.0,>=0.4.0
Requires-Dist: stamina<26.0.0,>=25.1.0
Requires-Dist: noneprompt<0.2.0,>=0.1.9
Requires-Dist: mongomock<4.4.0,>=4.3.0
Requires-Dist: jsonpickle<5.0.0,>=4.0.2
Requires-Dist: mslex<2.0.0,>=1.3.0
Requires-Dist: pexpect<5.0.0,>=4.9.0
Requires-Dist: pip>=25
Requires-Dist: dateparser<2.0.0,>=1.2.2
Provides-Extra: dev
Requires-Dist: pytest<9.0.0,>=8.0.0; extra == "dev"
Requires-Dist: pytest-cov<7.0.0,>=5.0.0; extra == "dev"
Requires-Dist: black<26.0.0,>=24.0.0; extra == "dev"
Requires-Dist: isort<7.0.0,>=5.13.0; extra == "dev"
Requires-Dist: mypy<2.0.0,>=1.14.0; extra == "dev"
Requires-Dist: flake8<8.0.0,>=7.0.0; extra == "dev"
Requires-Dist: pre-commit<5.0.0,>=3.0.0; extra == "dev"
Requires-Dist: freezegun<2.0.0,>=1.5.0; extra == "dev"
Requires-Dist: pytest-docker<4.0.0,>=3.0.0; extra == "dev"
Requires-Dist: pytest-asyncio<1.2.0,>=0.24.0; extra == "dev"
Requires-Dist: asgi-lifespan<3.0.0,>=2.1.0; extra == "dev"
Requires-Dist: tox<4.29.0,>=4.24.0; extra == "dev"
Requires-Dist: pytest-dependency<0.7.0,>=0.6.0; extra == "dev"
Requires-Dist: pytest-sugar<2.0.0,>=1.0.0; extra == "dev"
Requires-Dist: rust-just<2.0.0,>=1.42.4; extra == "dev"
Provides-Extra: doc
Requires-Dist: mkdocs-material<9.7.0,>=9.6.5; extra == "doc"
Requires-Dist: mkdocs-glightbox<0.5.0,>=0.4.0; extra == "doc"
Requires-Dist: mike<2.2.0,>=2.1.3; extra == "doc"
Provides-Extra: plugins
Requires-Dist: labtasker-plugin-task-count; extra == "plugins"
Requires-Dist: labtasker-plugin-script-generate; extra == "plugins"
Requires-Dist: labtasker-plugin-task-recency; extra == "plugins"
Dynamic: license-file
